[
   {
      "title":"@@org.joget.marketplace.MultiTabSliderFormatter.config@@",
      "properties":[
         {
            "label":"@@org.joget.marketplace.MultiTabSliderFormatter.hyperlink@@",
            "name":"href",
            "type":"textfield",
            "description":"@@org.joget.marketplace.MultiTabSliderFormatter.hyperlink.desc@@"
         },
         
         {
            "name":"parameters",
            "label":"@@datalist.hyperlinkdatalistaction.hyperlinkParameters@@",
            "type":"gridCombine",
            "columns":[
               {
                  "key":"hrefParam",
                  "label":"@@datalist.hyperlinkdatalistaction.hyperlinkParamName@@"
               },
               {
                  "key":"hrefColumn",
                  "label":"@@datalist.hyperlinkdatalistaction.columnName@@",
                  "type":"autocomplete",
                  "options_callback":"DatalistBuilder.getColumnOptions"
               }
            ],
            "value":[
               {
                  "hrefParam":"id",
                  "hrefColumn":"id"
               }
            ]
         },
         {
            "label":"@@org.joget.marketplace.MultiTabSliderFormatter.tabNameColumn@@",
            "name":"tabNameColumn",
            "type":"selectbox",
            "description":"@@org.joget.marketplace.MultiTabSliderFormatter.tabNameColumn.desc@@",
            "options_callback":"DatalistBuilder.getColumnOptions",
            "required":"false"
         },
         {
            "label":"@@datalist.hyperlinkdatalistaction.label@@",
            "name":"label",
            "type":"textfield",
            "description":"@@datalist.hyperlinkdatalistaction.label.desc@@",
            "value":"Open",
            "required":"false"
         },
         {
            "label":"@@org.joget.marketplace.MultiTabSliderFormatter.sliderWidth@@",
            "name":"width",
            "type":"textfield",
            "value":"50%",
            "required":"true"
         },
         {
            "label":"@@org.joget.marketplace.MultiTabSliderFormatter.editMode@@",
            "name":"editMode",
            "type":"checkbox",
            "value":"true",
            "description":"@@org.joget.marketplace.MultiTabSliderFormatter.editMode.desc@@"
         }
      ]
   },
   {
      "title":"@@org.joget.marketplace.MultiTabSliderFormatter.dockStyling@@",
      "properties":[
         {
            "label":"@@org.joget.marketplace.MultiTabSliderFormatter.dockBackground@@",
            "name":"dockBackground",
            "type":"textfield",
            "value":"linear-gradient(135deg, rgba(17, 23, 53, 0.95), rgba(33, 45, 85, 0.95))",
            "description":"@@org.joget.marketplace.MultiTabSliderFormatter.dockBackground.desc@@"
         },
         {
            "label":"@@org.joget.marketplace.MultiTabSliderFormatter.dockBorder@@",
            "name":"dockBorder",
            "type":"color",
            "value":"#ffffff26",
            "description":"@@org.joget.marketplace.MultiTabSliderFormatter.dockBorder.desc@@"
         },
         {
            "label":"@@org.joget.marketplace.MultiTabSliderFormatter.tabBackground@@",
            "name":"tabBackground",
            "type":"color",
            "value":"#ffffff1f",
            "description":"@@org.joget.marketplace.MultiTabSliderFormatter.tabBackground.desc@@"
         },
         {
            "label":"@@org.joget.marketplace.MultiTabSliderFormatter.tabActiveBackground@@",
            "name":"tabActiveBackground",
            "type":"color",
            "value":"#007bff",
            "description":"@@org.joget.marketplace.MultiTabSliderFormatter.tabActiveBackground.desc@@"
         },
         {
            "label":"@@org.joget.marketplace.MultiTabSliderFormatter.tabTextColor@@",
            "name":"tabTextColor",
            "type":"color",
            "value":"#ffffffe6",
            "description":"@@org.joget.marketplace.MultiTabSliderFormatter.tabTextColor.desc@@"
         },
         {
            "label":"@@org.joget.marketplace.MultiTabSliderFormatter.buttonBackground@@",
            "name":"buttonBackground",
            "type":"color",
            "value":"#6c757d26",
            "description":"@@org.joget.marketplace.MultiTabSliderFormatter.buttonBackground.desc@@"
         },
         {
            "label":"@@org.joget.marketplace.MultiTabSliderFormatter.buttonHoverBackground@@",
            "name":"buttonHoverBackground",
            "type":"color",
            "value":"#dc3545cc",
            "description":"@@org.joget.marketplace.MultiTabSliderFormatter.buttonHoverBackground.desc@@"
         },
         {
            "label":"@@org.joget.marketplace.MultiTabSliderFormatter.fontSize@@",
            "name":"fontSize",
            "type":"selectbox",
            "value":"normal",
            "options":[
               {
                  "label":"@@org.joget.marketplace.MultiTabSliderFormatter.fontSize.small@@",
                  "value":"small"
               },
               {
                  "label":"@@org.joget.marketplace.MultiTabSliderFormatter.fontSize.normal@@",
                  "value":"normal"
               },
               {
                  "label":"@@org.joget.marketplace.MultiTabSliderFormatter.fontSize.large@@",
                  "value":"large"
               },
               {
                  "label":"@@org.joget.marketplace.MultiTabSliderFormatter.fontSize.xlarge@@",
                  "value":"xlarge"
               }
            ]
         },
         {
            "label":"@@org.joget.marketplace.MultiTabSliderFormatter.fontWeight@@",
            "name":"fontWeight",
            "type":"selectbox",
            "value":"medium",
            "options":[
               {
                  "label":"@@org.joget.marketplace.MultiTabSliderFormatter.fontWeight.normal@@",
                  "value":"normal"
               },
               {
                  "label":"@@org.joget.marketplace.MultiTabSliderFormatter.fontWeight.medium@@",
                  "value":"medium"
               },
               {
                  "label":"@@org.joget.marketplace.MultiTabSliderFormatter.fontWeight.bold@@",
                  "value":"bold"
               },
               {
                  "label":"@@org.joget.marketplace.MultiTabSliderFormatter.fontWeight.bolder@@",
                  "value":"bolder"
               }
            ]
         },
         {
            "label":"@@org.joget.marketplace.MultiTabSliderFormatter.borderRadius@@",
            "name":"borderRadius",
            "type":"selectbox",
            "value":"medium",
            "options":[
               {
                  "label":"@@org.joget.marketplace.MultiTabSliderFormatter.borderRadius.none@@",
                  "value":"none"
               },
               {
                  "label":"@@org.joget.marketplace.MultiTabSliderFormatter.borderRadius.small@@",
                  "value":"small"
               },
               {
                  "label":"@@org.joget.marketplace.MultiTabSliderFormatter.borderRadius.medium@@",
                  "value":"medium"
               },
               {
                  "label":"@@org.joget.marketplace.MultiTabSliderFormatter.borderRadius.large@@",
                  "value":"large"
               }
            ]
         },
         {
            "label":"@@org.joget.marketplace.MultiTabSliderFormatter.dockHeight@@",
            "name":"dockHeight",
            "type":"textfield",
            "value":"60px",
            "description":"@@org.joget.marketplace.MultiTabSliderFormatter.dockHeight.desc@@"
         },
         {
            "label":"@@org.joget.marketplace.MultiTabSliderFormatter.dockPadding@@",
            "name":"dockPadding",
            "type":"textfield",
            "value":"8px 12px",
            "description":"@@org.joget.marketplace.MultiTabSliderFormatter.dockPadding.desc@@"
         },
         {
            "label":"@@org.joget.marketplace.MultiTabSliderFormatter.tabPadding@@",
            "name":"tabPadding",
            "type":"textfield",
            "value":"8px 16px",
            "description":"@@org.joget.marketplace.MultiTabSliderFormatter.tabPadding.desc@@"
         },
         {
            "label":"@@org.joget.marketplace.MultiTabSliderFormatter.tabMinWidth@@",
            "name":"tabMinWidth",
            "type":"textfield",
            "value":"120px",
            "description":"@@org.joget.marketplace.MultiTabSliderFormatter.tabMinWidth.desc@@"
         },
         {
            "label":"@@org.joget.marketplace.MultiTabSliderFormatter.tabMaxWidth@@",
            "name":"tabMaxWidth",
            "type":"textfield",
            "value":"200px",
            "description":"@@org.joget.marketplace.MultiTabSliderFormatter.tabMaxWidth.desc@@"
         },
         {
            "label":"@@org.joget.marketplace.MultiTabSliderFormatter.controlButtonSize@@",
            "name":"controlButtonSize",
            "type":"textfield",
            "value":"36px",
            "description":"@@org.joget.marketplace.MultiTabSliderFormatter.controlButtonSize.desc@@"
         },
         {
            "label":"@@org.joget.marketplace.MultiTabSliderFormatter.tabListGap@@",
            "name":"tabListGap",
            "type":"textfield",
            "value":"6px",
            "description":"Gap between tabs in the tab list"
         },
         {
            "label":"@@org.joget.marketplace.MultiTabSliderFormatter.tabListPadding@@",
            "name":"tabListPadding",
            "type":"textfield",
            "value":"0 8px",
            "description":"Padding around the tab list container"
         },
         {
            "label":"@@org.joget.marketplace.MultiTabSliderFormatter.controlsGap@@",
            "name":"controlsGap",
            "type":"textfield",
            "value":"8px",
            "description":"Gap between control buttons"
         },
         {
            "label":"@@org.joget.marketplace.MultiTabSliderFormatter.tabCloseButtonOpacity@@",
            "name":"tabCloseButtonOpacity",
            "type":"textfield",
            "value":"0.7",
            "description":"Opacity of tab close button when visible"
         }
      ]
   },
   {
      "title":"@@dbuilder.displayType@@",
      "properties":[
         {
            "label":"@@dbuilder.displayType@@",
            "name":"link-css-display-type",
            "type":"selectbox",
            "value":"btn btn-sm btn-primary",
            "options":[
               {
                  "label":"@@dbuilder.default@@",
                  "value":""
               },
               {
                  "label":"@@dbuilder.btn.link@@",
                  "value":"btn btn-link"
               },
               {
                  "label":"@@dbuilder.btn.primary@@",
                  "value":"btn btn-sm btn-primary"
               },
               {
                  "label":"@@dbuilder.btn.secondary@@",
                  "value":"btn btn-sm btn-secondary"
               },
               {
                  "label":"@@dbuilder.btn.success@@",
                  "value":"btn btn-sm btn-success"
               },
               {
                  "label":"@@dbuilder.btn.danger@@",
                  "value":"btn btn-sm btn-danger"
               },
               {
                  "label":"@@dbuilder.btn.warning@@",
                  "value":"btn btn-sm btn-warning"
               },
               {
                  "label":"@@dbuilder.btn.info@@",
                  "value":"btn btn-sm btn-info"
               },
               {
                  "label":"@@dbuilder.btn.light@@",
                  "value":"btn btn-sm btn-light"
               },
               {
                  "label":"@@dbuilder.btn.dark@@",
                  "value":"btn btn-sm btn-dark"
               }
            ]
         }
      ]
   }
]
